explorer/__init__.py
explorer/actions.py
explorer/admin.py
explorer/app_settings.py
explorer/apps.py
explorer/charts.py
explorer/exporters.py
explorer/forms.py
explorer/models.py
explorer/permissions.py
explorer/schema.py
explorer/tasks.py
explorer/telemetry.py
explorer/urls.py
explorer/utils.py
explorer/assistant/__init__.py
explorer/assistant/forms.py
explorer/assistant/models.py
explorer/assistant/urls.py
explorer/assistant/utils.py
explorer/assistant/views.py
explorer/ee/LICENSE
explorer/ee/__init__.py
explorer/ee/urls.py
explorer/ee/db_connections/__init__.py
explorer/ee/db_connections/admin.py
explorer/ee/db_connections/create_sqlite.py
explorer/ee/db_connections/forms.py
explorer/ee/db_connections/mime.py
explorer/ee/db_connections/models.py
explorer/ee/db_connections/type_infer.py
explorer/ee/db_connections/utils.py
explorer/ee/db_connections/views.py
explorer/locale/ru/LC_MESSAGES/django.mo
explorer/locale/ru/LC_MESSAGES/django.po
explorer/locale/zh_Hans/LC_MESSAGES/django.mo
explorer/locale/zh_Hans/LC_MESSAGES/django.po
explorer/migrations/0001_initial.py
explorer/migrations/0002_auto_20150501_1515.py
explorer/migrations/0003_query_snapshot.py
explorer/migrations/0004_querylog_duration.py
explorer/migrations/0005_auto_20160105_2052.py
explorer/migrations/0006_query_connection.py
explorer/migrations/0007_querylog_connection.py
explorer/migrations/0008_auto_20190308_1642.py
explorer/migrations/0009_auto_20201009_0547.py
explorer/migrations/0010_sql_required.py
explorer/migrations/0011_query_favorites.py
explorer/migrations/0012_alter_queryfavorite_query_alter_queryfavorite_user.py
explorer/migrations/0013_querylog_error_querylog_success.py
explorer/migrations/0014_promptlog.py
explorer/migrations/0015_explorervalue.py
explorer/migrations/0016_alter_explorervalue_key.py
explorer/migrations/0017_databaseconnection.py
explorer/migrations/0018_alter_databaseconnection_host_and_more.py
explorer/migrations/0019_alter_databaseconnection_engine.py
django_sql_explorer-5.3.dist-info/AUTHORS
django_sql_explorer-5.3.dist-info/LICENSE
django_sql_explorer-5.3.dist-info/METADATA
django_sql_explorer-5.3.dist-info/WHEEL
django_sql_explorer-5.3.dist-info/top_level.txt
django_sql_explorer-5.3.dist-info/RECORD
