Metadata-Version: 2.1
Name: django-sql-explorer
Version: 5.3
Summary: SQL Reporting that Just Works. Fast, simple, and confusion-free.Write and share queries in a delightful SQL editor, with AI assistance
Home-page: https://www.sqlexplorer.io
Author: Chris Clark
Author-email: chris@sqlexplorer.io
Maintainer: Chris Clark
Maintainer-email: chris@sqlexplorer.io
License: MIT
Project-URL: Changes, https://django-sql-explorer.readthedocs.io/en/latest/history.html
Project-URL: Documentation, https://django-sql-explorer.readthedocs.io/en/latest/
Project-URL: Issues, https://github.com/explorerhq/sql-explorer/issues
Keywords: django sql explorer reports reporting csv json database query
Classifier: Development Status :: 5 - Production/Stable
Classifier: Intended Audience :: Developers
Classifier: License :: OSI Approved :: MIT License
Classifier: Topic :: Utilities
Classifier: Framework :: Django :: 3.2
Classifier: Framework :: Django :: 4.2
Classifier: Framework :: Django :: 5.0
Classifier: Programming Language :: Python :: 3
Classifier: Programming Language :: Python :: 3.10
Classifier: Programming Language :: Python :: 3.11
Classifier: Programming Language :: Python :: 3.12
Classifier: Programming Language :: Python :: 3 :: Only
Requires-Python: >=3.8
License-File: LICENSE
License-File: AUTHORS
Requires-Dist: Django>=3.2
Requires-Dist: sqlparse>=0.4.0
Requires-Dist: requests>=2.2
Requires-Dist: django-cryptography-django5==2.2
Requires-Dist: cryptography>=42.0
Provides-Extra: charts
Requires-Dist: matplotlib>=3.9; extra == "charts"
Provides-Extra: snapshots
Requires-Dist: boto3>=1.30.0; extra == "snapshots"
Requires-Dist: celery>=4.0; extra == "snapshots"
Provides-Extra: xls
Requires-Dist: xlsxwriter>=1.3.6; extra == "xls"
Provides-Extra: assistant
Requires-Dist: openai>=1.6.1; extra == "assistant"
Provides-Extra: uploads
Requires-Dist: python-dateutil>=2.9; extra == "uploads"
Requires-Dist: pandas>=2.2; extra == "uploads"
Requires-Dist: boto3>=1.30.0; extra == "uploads"
